aws_icons.py
icons/Analytics_AWSDataPipeline.png
icons/Analytics_AmazonEMR.png
icons/Analytics_AmazonEMR_EMRengine.png
icons/Analytics_AmazonEMR_EMRengineMapRM3.png
icons/Analytics_AmazonEMR_EMRengineMapRM5.png
icons/Analytics_AmazonEMR_EMRengineMapRM7.png
icons/Analytics_AmazonEMR_HDFScluster.png
icons/Analytics_AmazonEMR_cluster.png
icons/Analytics_AmazonElasticsearchService.png
icons/Analytics_AmazonKinesis.png
icons/Analytics_AmazonKinesis_AmazonKinesis-enabledapp.png
icons/Analytics_AmazonKinesis_AmazonKinesisAnalytics.png
icons/Analytics_AmazonKinesis_AmazonKinesisFirehose.png
icons/Analytics_AmazonKinesis_AmazonKinesisStreams.png
icons/Analytics_AmazonMachineLearning.png
icons/Analytics_AmazonQuickSight.png
icons/Application-Services_AmazonAPIGateway.png
icons/Application-Services_AmazonAppStream.png
icons/Application-Services_AmazonCloudSearch.png
icons/Application-Services_AmazonCloudSearch_SDFmetadata.png
icons/Application-Services_AmazonElasticTranscoder.png
icons/Application-Services_AmazonSES.png
icons/Application-Services_AmazonSES_email.png
icons/Application-Services_AmazonSQS.png
icons/Application-Services_AmazonSQS_message.png
icons/Application-Services_AmazonSQS_queue.png
icons/Application-Services_AmazonSWF.png
icons/Application-Services_AmazonSWF_decider.png
icons/Application-Services_AmazonSWF_worker.png
icons/Compute_AWSElasticBeanstalk.png
icons/Compute_AWSElasticBeanstalk_application.png
icons/Compute_AWSElasticBeanstalk_deployment.png
icons/Compute_AWSLambda.png
icons/Compute_AmazonEC2.png
icons/Compute_AmazonEC2_AMI.png
icons/Compute_AmazonEC2_AutoScaling.png
icons/Compute_AmazonEC2_DBoninstance.png
icons/Compute_AmazonEC2_ElasticIP.png
icons/Compute_AmazonEC2_Spotfleet.png
icons/Compute_AmazonEC2_Spotinstance.png
icons/Compute_AmazonEC2_instance.png
icons/Compute_AmazonEC2_instances.png
icons/Compute_AmazonEC2_instancewithCloudWatch.png
icons/Compute_AmazonEC2_optimizedinstance.png
terraform_aws_icons-0.1.0.dist-info/DESCRIPTION.rst
terraform_aws_icons-0.1.0.dist-info/METADATA
terraform_aws_icons-0.1.0.dist-info/RECORD
terraform_aws_icons-0.1.0.dist-info/WHEEL
terraform_aws_icons-0.1.0.dist-info/entry_points.txt
terraform_aws_icons-0.1.0.dist-info/metadata.json
terraform_aws_icons-0.1.0.dist-info/top_level.txt
