Metadata-Version: 2.0
Name: terraform-aws-icons
Version: 0.1.0
Summary: Annotate Terraform graphs with AWS icons.
Home-page: https://github.com/github/terraform-aws-icons
Author: TabbedOut
Author-email: github@tabbedout.com
License: MIT
Platform: any
Classifier: Development Status :: 4 - Beta
Classifier: Environment :: Console
Classifier: Programming Language :: Python
Classifier: Programming Language :: Python :: 2
Classifier: Programming Language :: Python :: 3
